{"updated_at":"2026-04-15 09:30","scan_failed":false,"sample_size":258,"signal_count":19,"crowding_index":{"high_base":0.047,"ma_pullback":0.008,"retest":0.027},"signal_tracking":[{"code":"1528","name":"恩德","type":"high_base","label":"強整再突","strength":"strong","trigger_date":"2026-04-15","trigger_price":30.44,"entry":30.35,"stop_loss":25.08,"atr_stop":25.08,"target":53.12,"rr":4.32,"confirmations":5,"confirmation_flags":["RS強勢","量能擴張","個股多頭","大盤多頭","均量線對齊"],"exit_style":"trailing","status":"open","repeat":false,"is_pyramid":false,"sector_key":"電機機械","sector_phase":"主升回檔","current_price":30.35,"days_held":1,"gain_pct":-0.3,"resolved_date":null,"rs_pct_at_trigger":82,"vol_ratio_at_trigger":1.62,"market_regime_at_trigger":"bull","max_gain_pct":0.0,"max_loss_pct":-0.3,"day_of_max_gain":0,"exit_reason":null},{"code":"2049","name":"上銀","type":"high_base","label":"強整再突","strength":"strong","trigger_date":"2026-04-15","trigger_price":294.88,"entry":281.0,"stop_loss":239.97,"atr_stop":243.6,"target":458.25,"rr":4.32,"confirmations":5,"confirmation_flags":["RS強勢","量能擴張","個股多頭","大盤多頭","均量線對齊"],"exit_style":"trailing","status":"open","repeat":false,"is_pyramid":false,"sector_key":"其他","sector_phase":"整理觀察","current_price":282.0,"days_held":1,"gain_pct":-4.37,"resolved_date":null,"rs_pct_at_trigger":83,"vol_ratio_at_trigger":4.31,"market_regime_at_trigger":"bull","max_gain_pct":0.0,"max_loss_pct":-4.37,"day_of_max_gain":0,"exit_reason":null},{"code":"2399","name":"映泰","type":"high_base","label":"強整再突","strength":"strong","trigger_date":"2026-04-15","trigger_price":37.16,"entry":37.05,"stop_loss":30.9,"atr_stop":30.9,"target":63.62,"rr":4.32,"confirmations":5,"confirmation_flags":["RS強勢","量能擴張","個股多頭","大盤多頭","均量線對齊"],"exit_style":"trailing","status":"open","repeat":false,"is_pyramid":false,"sector_key":"","sector_phase":"","current_price":37.05,"days_held":1,"gain_pct":-0.3,"resolved_date":null,"rs_pct_at_trigger":84,"vol_ratio_at_trigger":1.59,"market_regime_at_trigger":"bull","max_gain_pct":0.0,"max_loss_pct":-0.3,"day_of_max_gain":0,"exit_reason":null},{"code":"2495","name":"普安","type":"high_base","label":"強整再突","strength":"strong","trigger_date":"2026-04-15","trigger_price":45.34,"entry":45.2,"stop_loss":37.05,"atr_stop":39.18,"target":80.41,"rr":4.32,"confirmations":5,"confirmation_flags":["RS強勢","量能擴張","個股多頭","大盤多頭","均量線對齊"],"exit_style":"trailing","status":"open","repeat":false,"is_pyramid":false,"sector_key":"電腦週邊","sector_phase":"主升回檔","current_price":45.2,"days_held":1,"gain_pct":-0.31,"resolved_date":null,"rs_pct_at_trigger":80,"vol_ratio_at_trigger":1.79,"market_regime_at_trigger":"bull","max_gain_pct":0.0,"max_loss_pct":-0.31,"day_of_max_gain":0,"exit_reason":null},{"code":"3044","name":"健鼎","type":"high_base","label":"強整再突","strength":"strong","trigger_date":"2026-04-15","trigger_price":417.75,"entry":401.0,"stop_loss":354.85,"atr_stop":354.85,"target":600.37,"rr":4.32,"confirmations":5,"confirmation_flags":["RS強勢","量能擴張","個股多頭","大盤多頭","均量線對齊"],"exit_style":"trailing","status":"open","repeat":false,"is_pyramid":false,"sector_key":"電子零組件","sector_phase":"整理觀察","current_price":402.0,"days_held":1,"gain_pct":-3.77,"resolved_date":null,"rs_pct_at_trigger":73,"vol_ratio_at_trigger":2.31,"market_regime_at_trigger":"bull","max_gain_pct":0.0,"max_loss_pct":-3.77,"day_of_max_gain":0,"exit_reason":null},{"code":"3450","name":"聯鈞","type":"high_base","label":"強整再突","strength":"strong","trigger_date":"2026-04-15","trigger_price":346.54,"entry":345.5,"stop_loss":285.45,"atr_stop":292.2,"target":604.92,"rr":4.32,"confirmations":5,"confirmation_flags":["RS強勢","量能擴張","個股多頭","大盤多頭","均量線對齊"],"exit_style":"trailing","status":"open","repeat":false,"is_pyramid":false,"sector_key":"半導體","sector_phase":"整理觀察","current_price":345.5,"days_held":1,"gain_pct":-0.3,"resolved_date":null,"rs_pct_at_trigger":79,"vol_ratio_at_trigger":1.46,"market_regime_at_trigger":"bull","max_gain_pct":0.0,"max_loss_pct":-0.3,"day_of_max_gain":0,"exit_reason":null},{"code":"3711","name":"日月光投控","type":"high_base","label":"強整再突","strength":"strong","trigger_date":"2026-04-15","trigger_price":461.38,"entry":444.0,"stop_loss":334.93,"atr_stop":388.2,"target":915.18,"rr":4.32,"confirmations":5,"confirmation_flags":["RS強勢","量能擴張","個股多頭","大盤多頭","均量線對齊"],"exit_style":"trailing","status":"open","repeat":false,"is_pyramid":false,"sector_key":"半導體","sector_phase":"整理觀察","current_price":446.5,"days_held":1,"gain_pct":-3.23,"resolved_date":null,"rs_pct_at_trigger":88,"vol_ratio_at_trigger":1.32,"market_regime_at_trigger":"bull","max_gain_pct":0.0,"max_loss_pct":-3.23,"day_of_max_gain":0,"exit_reason":null},{"code":"6271","name":"同欣電","type":"high_base","label":"強整再突","strength":"strong","trigger_date":"2026-04-15","trigger_price":188.56,"entry":182.5,"stop_loss":157.01,"atr_stop":159.28,"target":292.62,"rr":4.32,"confirmations":5,"confirmation_flags":["RS強勢","量能擴張","個股多頭","大盤多頭","均量線對齊"],"exit_style":"trailing","status":"open","repeat":false,"is_pyramid":false,"sector_key":"","sector_phase":"","current_price":183.0,"days_held":1,"gain_pct":-2.95,"resolved_date":null,"rs_pct_at_trigger":83,"vol_ratio_at_trigger":3.7,"market_regime_at_trigger":"bull","max_gain_pct":0.0,"max_loss_pct":-2.95,"day_of_max_gain":0,"exit_reason":null},{"code":"6456","name":"GIS-KY","type":"high_base","label":"強整再突","strength":"strong","trigger_date":"2026-04-15","trigger_price":70.31,"entry":70.1,"stop_loss":58.16,"atr_stop":60.3,"target":121.68,"rr":4.32,"confirmations":5,"confirmation_flags":["RS強勢","量能擴張","個股多頭","大盤多頭","均量線對齊"],"exit_style":"trailing","status":"open","repeat":false,"is_pyramid":false,"sector_key":"","sector_phase":"","current_price":70.1,"days_held":1,"gain_pct":-0.3,"resolved_date":null,"rs_pct_at_trigger":89,"vol_ratio_at_trigger":3.98,"market_regime_at_trigger":"bull","max_gain_pct":0.0,"max_loss_pct":-0.3,"day_of_max_gain":0,"exit_reason":null},{"code":"6909","name":"創控","type":"high_base","label":"強整再突","strength":"strong","trigger_date":"2026-04-15","trigger_price":58.17,"entry":58.0,"stop_loss":48.02,"atr_stop":49.25,"target":101.11,"rr":4.32,"confirmations":5,"confirmation_flags":["RS強勢","量能擴張","個股多頭","大盤多頭","均量線對齊"],"exit_style":"trailing","status":"open","repeat":false,"is_pyramid":false,"sector_key":"電機機械","sector_phase":"主升回檔","current_price":52.8,"days_held":1,"gain_pct":0.0,"resolved_date":null,"rs_pct_at_trigger":76,"vol_ratio_at_trigger":2.87,"market_regime_at_trigger":"bull","max_gain_pct":0.0,"max_loss_pct":0.0,"day_of_max_gain":0,"exit_reason":null},{"code":"8150","name":"南茂","type":"high_base","label":"強整再突","strength":"strong","trigger_date":"2026-04-15","trigger_price":69.51,"entry":66.8,"stop_loss":58.52,"atr_stop":58.52,"target":102.57,"rr":4.32,"confirmations":5,"confirmation_flags":["RS強勢","量能擴張","個股多頭","大盤多頭","均量線對齊"],"exit_style":"trailing","status":"open","repeat":false,"is_pyramid":false,"sector_key":"","sector_phase":"","current_price":67.0,"days_held":1,"gain_pct":-3.61,"resolved_date":null,"rs_pct_at_trigger":72,"vol_ratio_at_trigger":2.92,"market_regime_at_trigger":"bull","max_gain_pct":0.0,"max_loss_pct":-3.61,"day_of_max_gain":0,"exit_reason":null},{"code":"2010","name":"春源","type":"ma_pullback","label":"均線回測(主升型)","strength":"medium","trigger_date":"2026-04-15","trigger_price":25.58,"entry":25.1,"stop_loss":23.73,"atr_stop":23.73,"target":28.06,"rr":2.16,"confirmations":1,"confirmation_flags":["大盤多頭"],"exit_style":"fixed","status":"open","repeat":false,"is_pyramid":false,"sector_key":"","sector_phase":"","current_price":25.35,"days_held":1,"gain_pct":0.0,"resolved_date":null,"rs_pct_at_trigger":67,"vol_ratio_at_trigger":0.83,"market_regime_at_trigger":"bull","max_gain_pct":0.0,"max_loss_pct":0.0,"day_of_max_gain":0,"exit_reason":null},{"code":"2010","name":"春源","type":"retest","label":"縮量回測(主升型)","strength":"medium","trigger_date":"2026-04-15","trigger_price":25.58,"entry":25.1,"stop_loss":23.73,"atr_stop":23.73,"target":28.06,"rr":2.16,"confirmations":1,"confirmation_flags":["大盤多頭"],"exit_style":"fixed","status":"open","repeat":false,"is_pyramid":false,"sector_key":"","sector_phase":"","current_price":25.35,"days_held":1,"gain_pct":0.0,"resolved_date":null,"rs_pct_at_trigger":67,"vol_ratio_at_trigger":0.83,"market_regime_at_trigger":"bull","max_gain_pct":0.0,"max_loss_pct":0.0,"day_of_max_gain":0,"exit_reason":null},{"code":"2393","name":"億光","type":"ma_pullback","label":"均線回測(主升型)","strength":"medium","trigger_date":"2026-04-15","trigger_price":72.06,"entry":70.7,"stop_loss":65.75,"atr_stop":65.75,"target":81.39,"rr":2.16,"confirmations":2,"confirmation_flags":["RS強勢","大盤多頭"],"exit_style":"fixed","status":"open","repeat":false,"is_pyramid":false,"sector_key":"","sector_phase":"","current_price":71.3,"days_held":1,"gain_pct":0.0,"resolved_date":null,"rs_pct_at_trigger":74,"vol_ratio_at_trigger":0.39,"market_regime_at_trigger":"bull","max_gain_pct":0.0,"max_loss_pct":0.0,"day_of_max_gain":0,"exit_reason":null},{"code":"2393","name":"億光","type":"retest","label":"縮量回測(主升型)","strength":"medium","trigger_date":"2026-04-15","trigger_price":72.06,"entry":70.7,"stop_loss":65.75,"atr_stop":65.75,"target":81.39,"rr":2.16,"confirmations":2,"confirmation_flags":["RS強勢","大盤多頭"],"exit_style":"fixed","status":"open","repeat":false,"is_pyramid":false,"sector_key":"","sector_phase":"","current_price":71.3,"days_held":1,"gain_pct":0.0,"resolved_date":null,"rs_pct_at_trigger":74,"vol_ratio_at_trigger":0.39,"market_regime_at_trigger":"bull","max_gain_pct":0.0,"max_loss_pct":0.0,"day_of_max_gain":0,"exit_reason":null},{"code":"2883","name":"凱基金","type":"ma_pullback","label":"均線回測(主升型)","strength":"medium","trigger_date":"2026-04-15","trigger_price":21.1,"entry":20.85,"stop_loss":19.62,"atr_stop":19.62,"target":23.51,"rr":2.16,"confirmations":1,"confirmation_flags":["大盤多頭"],"exit_style":"fixed","status":"open","repeat":false,"is_pyramid":false,"sector_key":"金融保險","sector_phase":"整理觀察","current_price":20.75,"days_held":1,"gain_pct":-1.66,"resolved_date":null,"rs_pct_at_trigger":64,"vol_ratio_at_trigger":0.56,"market_regime_at_trigger":"bull","max_gain_pct":0.0,"max_loss_pct":-1.66,"day_of_max_gain":0,"exit_reason":null},{"code":"2883","name":"凱基金","type":"retest","label":"縮量回測(主升型)","strength":"medium","trigger_date":"2026-04-15","trigger_price":21.1,"entry":20.85,"stop_loss":19.62,"atr_stop":19.62,"target":23.51,"rr":2.16,"confirmations":1,"confirmation_flags":["大盤多頭"],"exit_style":"fixed","status":"open","repeat":false,"is_pyramid":false,"sector_key":"金融保險","sector_phase":"整理觀察","current_price":20.75,"days_held":1,"gain_pct":-1.66,"resolved_date":null,"rs_pct_at_trigger":64,"vol_ratio_at_trigger":0.56,"market_regime_at_trigger":"bull","max_gain_pct":0.0,"max_loss_pct":-1.66,"day_of_max_gain":0,"exit_reason":null},{"code":"3023","name":"信邦","type":"ma_pullback","label":"均線回測(主升型)","strength":"medium","trigger_date":"2026-04-15","trigger_price":274.87,"entry":268.0,"stop_loss":241.85,"atr_stop":241.85,"target":324.48,"rr":2.16,"confirmations":2,"confirmation_flags":["RS強勢","大盤多頭"],"exit_style":"fixed","status":"open","repeat":false,"is_pyramid":false,"sector_key":"","sector_phase":"","current_price":268.0,"days_held":1,"gain_pct":0.0,"resolved_date":null,"rs_pct_at_trigger":82,"vol_ratio_at_trigger":0.43,"market_regime_at_trigger":"bull","max_gain_pct":0.0,"max_loss_pct":0.0,"day_of_max_gain":0,"exit_reason":null},{"code":"3023","name":"信邦","type":"retest","label":"縮量回測(主升型)","strength":"medium","trigger_date":"2026-04-15","trigger_price":274.87,"entry":268.0,"stop_loss":241.85,"atr_stop":241.85,"target":324.48,"rr":2.16,"confirmations":2,"confirmation_flags":["RS強勢","大盤多頭"],"exit_style":"fixed","status":"open","repeat":false,"is_pyramid":false,"sector_key":"","sector_phase":"","current_price":268.0,"days_held":1,"gain_pct":0.0,"resolved_date":null,"rs_pct_at_trigger":82,"vol_ratio_at_trigger":0.43,"market_regime_at_trigger":"bull","max_gain_pct":0.0,"max_loss_pct":0.0,"day_of_max_gain":0,"exit_reason":null},{"code":"3715","name":"定穎投控","type":"ma_pullback","label":"均線回測(主升型)","strength":"medium","trigger_date":"2026-04-15","trigger_price":192.96,"entry":185.0,"stop_loss":153.12,"atr_stop":153.12,"target":322.72,"rr":4.32,"confirmations":3,"confirmation_flags":["RS強勢","個股多頭","大盤多頭"],"exit_style":"fixed","status":"open","repeat":false,"is_pyramid":false,"sector_key":"電子零組件","sector_phase":"整理觀察","current_price":185.5,"days_held":1,"gain_pct":-3.87,"resolved_date":null,"rs_pct_at_trigger":83,"vol_ratio_at_trigger":0.55,"market_regime_at_trigger":"bull","max_gain_pct":0.0,"max_loss_pct":-3.87,"day_of_max_gain":0,"exit_reason":null},{"code":"1528","name":"恩德","type":"high_base","label":"強整再突","strength":"strong","trigger_date":"2026-04-15","trigger_price":30.44,"entry":30.35,"stop_loss":25.08,"atr_stop":25.08,"target":53.12,"rr":4.32,"confirmations":5,"confirmation_flags":["RS強勢","量能擴張","個股多頭","大盤多頭","均量線對齊"],"exit_style":"trailing","status":"open","repeat":true,"is_pyramid":false,"sector_key":"電機機械","sector_phase":"主升回檔","current_price":30.35,"days_held":0,"gain_pct":0.0,"resolved_date":null,"rs_pct_at_trigger":71,"vol_ratio_at_trigger":1.67,"market_regime_at_trigger":"bull","max_gain_pct":0.0,"max_loss_pct":0.0,"day_of_max_gain":0,"exit_reason":null},{"code":"2399","name":"映泰","type":"high_base","label":"強整再突","strength":"strong","trigger_date":"2026-04-15","trigger_price":37.16,"entry":37.05,"stop_loss":30.9,"atr_stop":30.9,"target":63.62,"rr":4.32,"confirmations":5,"confirmation_flags":["RS強勢","量能擴張","個股多頭","大盤多頭","均量線對齊"],"exit_style":"trailing","status":"open","repeat":true,"is_pyramid":false,"sector_key":"電腦週邊","sector_phase":"主升回檔","current_price":37.05,"days_held":0,"gain_pct":0.0,"resolved_date":null,"rs_pct_at_trigger":74,"vol_ratio_at_trigger":1.62,"market_regime_at_trigger":"bull","max_gain_pct":0.0,"max_loss_pct":0.0,"day_of_max_gain":0,"exit_reason":null},{"code":"2484","name":"希華","type":"high_base","label":"強整再突","strength":"strong","trigger_date":"2026-04-15","trigger_price":37.96,"entry":36.65,"stop_loss":30.35,"atr_stop":30.35,"target":63.87,"rr":4.32,"confirmations":5,"confirmation_flags":["RS強勢","量能擴張","個股多頭","大盤多頭","均量線對齊"],"exit_style":"trailing","status":"open","repeat":false,"is_pyramid":false,"sector_key":"電子零組件","sector_phase":"整理觀察","current_price":36.65,"days_held":0,"gain_pct":0.0,"resolved_date":null,"rs_pct_at_trigger":85,"vol_ratio_at_trigger":3.32,"market_regime_at_trigger":"bull","max_gain_pct":0.0,"max_loss_pct":0.0,"day_of_max_gain":0,"exit_reason":null},{"code":"6456","name":"GIS-KY","type":"high_base","label":"強整再突","strength":"strong","trigger_date":"2026-04-15","trigger_price":70.31,"entry":70.1,"stop_loss":58.17,"atr_stop":60.3,"target":121.64,"rr":4.32,"confirmations":5,"confirmation_flags":["RS強勢","量能擴張","個股多頭","大盤多頭","均量線對齊"],"exit_style":"trailing","status":"open","repeat":true,"is_pyramid":false,"sector_key":"電子零組件","sector_phase":"整理觀察","current_price":70.1,"days_held":0,"gain_pct":0.0,"resolved_date":null,"rs_pct_at_trigger":81,"vol_ratio_at_trigger":4.0,"market_regime_at_trigger":"bull","max_gain_pct":0.0,"max_loss_pct":0.0,"day_of_max_gain":0,"exit_reason":null},{"code":"3645","name":"達邁","type":"high_base","label":"強整再突","strength":"strong","trigger_date":"2026-04-15","trigger_price":93.88,"entry":93.5,"stop_loss":74.89,"atr_stop":79.83,"target":173.9,"rr":4.32,"confirmations":5,"confirmation_flags":["RS強勢","量能擴張","個股多頭","大盤多頭","均量線對齊"],"exit_style":"trailing","status":"open","repeat":false,"is_pyramid":false,"sector_key":"電子零組件","sector_phase":"整理觀察","current_price":93.5,"days_held":0,"gain_pct":0.0,"resolved_date":null,"rs_pct_at_trigger":86,"vol_ratio_at_trigger":2.3,"market_regime_at_trigger":"bull","max_gain_pct":0.0,"max_loss_pct":0.0,"day_of_max_gain":0,"exit_reason":null},{"code":"3711","name":"日月光投控","type":"high_base","label":"強整再突","strength":"strong","trigger_date":"2026-04-15","trigger_price":461.38,"entry":446.5,"stop_loss":335.4,"atr_stop":390.7,"target":926.45,"rr":4.32,"confirmations":5,"confirmation_flags":["RS強勢","量能擴張","個股多頭","大盤多頭","均量線對齊"],"exit_style":"trailing","status":"open","repeat":true,"is_pyramid":false,"sector_key":"半導體","sector_phase":"整理觀察","current_price":446.5,"days_held":0,"gain_pct":0.0,"resolved_date":null,"rs_pct_at_trigger":80,"vol_ratio_at_trigger":1.59,"market_regime_at_trigger":"bull","max_gain_pct":0.0,"max_loss_pct":0.0,"day_of_max_gain":0,"exit_reason":null},{"code":"2049","name":"上銀","type":"high_base","label":"強整再突","strength":"strong","trigger_date":"2026-04-15","trigger_price":294.88,"entry":282.0,"stop_loss":240.21,"atr_stop":244.6,"target":462.53,"rr":4.32,"confirmations":5,"confirmation_flags":["RS強勢","量能擴張","個股多頭","大盤多頭","均量線對齊"],"exit_style":"trailing","status":"open","repeat":true,"is_pyramid":false,"sector_key":"其他","sector_phase":"整理觀察","current_price":282.0,"days_held":0,"gain_pct":0.0,"resolved_date":null,"rs_pct_at_trigger":72,"vol_ratio_at_trigger":4.59,"market_regime_at_trigger":"bull","max_gain_pct":0.0,"max_loss_pct":0.0,"day_of_max_gain":0,"exit_reason":null},{"code":"6271","name":"同欣電","type":"high_base","label":"強整再突","strength":"strong","trigger_date":"2026-04-15","trigger_price":188.56,"entry":183.0,"stop_loss":157.11,"atr_stop":159.78,"target":294.84,"rr":4.32,"confirmations":5,"confirmation_flags":["RS強勢","量能擴張","個股多頭","大盤多頭","均量線對齊"],"exit_style":"trailing","status":"open","repeat":true,"is_pyramid":false,"sector_key":"半導體","sector_phase":"整理觀察","current_price":183.0,"days_held":0,"gain_pct":0.0,"resolved_date":null,"rs_pct_at_trigger":73,"vol_ratio_at_trigger":3.95,"market_regime_at_trigger":"bull","max_gain_pct":0.0,"max_loss_pct":0.0,"day_of_max_gain":0,"exit_reason":null},{"code":"6438","name":"迅得","type":"ma_pullback","label":"均線回測(主升型)","strength":"medium","trigger_date":"2026-04-15","trigger_price":182.41,"entry":176.0,"stop_loss":151.9,"atr_stop":151.9,"target":228.06,"rr":2.16,"confirmations":1,"confirmation_flags":["大盤多頭"],"exit_style":"fixed","status":"open","repeat":false,"is_pyramid":false,"sector_key":"電機機械","sector_phase":"主升回檔","current_price":176.0,"days_held":0,"gain_pct":0.0,"resolved_date":null,"rs_pct_at_trigger":65,"vol_ratio_at_trigger":0.43,"market_regime_at_trigger":"bull","max_gain_pct":0.0,"max_loss_pct":0.0,"day_of_max_gain":0,"exit_reason":null},{"code":"6438","name":"迅得","type":"retest","label":"縮量回測(主升型)","strength":"medium","trigger_date":"2026-04-15","trigger_price":182.41,"entry":176.0,"stop_loss":151.9,"atr_stop":151.9,"target":228.06,"rr":2.16,"confirmations":1,"confirmation_flags":["大盤多頭"],"exit_style":"fixed","status":"open","repeat":false,"is_pyramid":false,"sector_key":"電機機械","sector_phase":"主升回檔","current_price":176.0,"days_held":0,"gain_pct":0.0,"resolved_date":null,"rs_pct_at_trigger":65,"vol_ratio_at_trigger":0.43,"market_regime_at_trigger":"bull","max_gain_pct":0.0,"max_loss_pct":0.0,"day_of_max_gain":0,"exit_reason":null},{"code":"3715","name":"定穎投控","type":"ma_pullback","label":"均線回測(主升型)","strength":"medium","trigger_date":"2026-04-15","trigger_price":192.96,"entry":185.5,"stop_loss":153.62,"atr_stop":153.62,"target":323.22,"rr":4.32,"confirmations":3,"confirmation_flags":["RS強勢","個股多頭","大盤多頭"],"exit_style":"fixed","status":"open","repeat":true,"is_pyramid":false,"sector_key":"電子零組件","sector_phase":"整理觀察","current_price":185.5,"days_held":0,"gain_pct":0.0,"resolved_date":null,"rs_pct_at_trigger":72,"vol_ratio_at_trigger":0.64,"market_regime_at_trigger":"bull","max_gain_pct":0.0,"max_loss_pct":0.0,"day_of_max_gain":0,"exit_reason":null},{"code":"3715","name":"定穎投控","type":"retest","label":"縮量回測(主升型)","strength":"medium","trigger_date":"2026-04-15","trigger_price":192.96,"entry":185.5,"stop_loss":153.62,"atr_stop":153.62,"target":323.22,"rr":4.32,"confirmations":3,"confirmation_flags":["RS強勢","個股多頭","大盤多頭"],"exit_style":"fixed","status":"open","repeat":false,"is_pyramid":true,"sector_key":"電子零組件","sector_phase":"整理觀察","current_price":185.5,"days_held":0,"gain_pct":0.0,"resolved_date":null,"rs_pct_at_trigger":72,"vol_ratio_at_trigger":0.64,"market_regime_at_trigger":"bull","max_gain_pct":0.0,"max_loss_pct":0.0,"day_of_max_gain":0,"exit_reason":null},{"code":"2455","name":"全新","type":"retest","label":"縮量回測(主升型)","strength":"medium","trigger_date":"2026-04-15","trigger_price":283.41,"entry":275.0,"stop_loss":223.65,"atr_stop":223.65,"target":385.92,"rr":2.16,"confirmations":2,"confirmation_flags":["RS強勢","大盤多頭"],"exit_style":"fixed","status":"open","repeat":false,"is_pyramid":false,"sector_key":"半導體","sector_phase":"整理觀察","current_price":275.0,"days_held":0,"gain_pct":0.0,"resolved_date":null,"rs_pct_at_trigger":86,"vol_ratio_at_trigger":0.15,"market_regime_at_trigger":"bull","max_gain_pct":0.0,"max_loss_pct":0.0,"day_of_max_gain":0,"exit_reason":null},{"code":"2360","name":"致茂","type":"high_base","label":"強整再突","strength":"medium","trigger_date":"2026-04-15","trigger_price":2026.06,"entry":2020.0,"stop_loss":1350.17,"atr_stop":1680.72,"target":4913.67,"rr":4.32,"confirmations":4,"confirmation_flags":["RS強勢","個股多頭","大盤多頭","均量線對齊"],"exit_style":"trailing","status":"open","repeat":false,"is_pyramid":false,"sector_key":"電子工業","sector_phase":"高檔震盪","current_price":2020.0,"days_held":0,"gain_pct":0.0,"resolved_date":null,"rs_pct_at_trigger":93,"vol_ratio_at_trigger":0.69,"market_regime_at_trigger":"bull","max_gain_pct":0.0,"max_loss_pct":0.0,"day_of_max_gain":0,"exit_reason":null},{"code":"4989","name":"榮科","type":"high_base","label":"強整再突","strength":"medium","trigger_date":"2026-04-15","trigger_price":98.59,"entry":98.3,"stop_loss":69.91,"atr_stop":84.9,"target":220.94,"rr":4.32,"confirmations":4,"confirmation_flags":["RS強勢","個股多頭","大盤多頭","均量線對齊"],"exit_style":"trailing","status":"open","repeat":false,"is_pyramid":false,"sector_key":"鋼鐵","sector_phase":"整理觀察","current_price":98.3,"days_held":0,"gain_pct":0.0,"resolved_date":null,"rs_pct_at_trigger":90,"vol_ratio_at_trigger":0.64,"market_regime_at_trigger":"bull","max_gain_pct":0.0,"max_loss_pct":0.0,"day_of_max_gain":0,"exit_reason":null},{"code":"2383","name":"台光電","type":"high_base","label":"強整再突","strength":"medium","trigger_date":"2026-04-15","trigger_price":3886.62,"entry":3810.0,"stop_loss":2281.43,"atr_stop":3274.28,"target":10413.42,"rr":4.32,"confirmations":4,"confirmation_flags":["RS強勢","個股多頭","大盤多頭","均量線對齊"],"exit_style":"trailing","status":"open","repeat":false,"is_pyramid":false,"sector_key":"電子零組件","sector_phase":"整理觀察","current_price":3810.0,"days_held":0,"gain_pct":0.0,"resolved_date":null,"rs_pct_at_trigger":96,"vol_ratio_at_trigger":1.17,"market_regime_at_trigger":"bull","max_gain_pct":0.0,"max_loss_pct":0.0,"day_of_max_gain":0,"exit_reason":null},{"code":"3017","name":"奇鋐","type":"high_base","label":"強整再突","strength":"medium","trigger_date":"2026-04-15","trigger_price":2382.12,"entry":2325.0,"stop_loss":1759.88,"atr_stop":1984.83,"target":4766.32,"rr":4.32,"confirmations":4,"confirmation_flags":["RS強勢","個股多頭","大盤多頭","均量線對齊"],"exit_style":"trailing","status":"open","repeat":false,"is_pyramid":false,"sector_key":"電子零組件","sector_phase":"整理觀察","current_price":2325.0,"days_held":0,"gain_pct":0.0,"resolved_date":null,"rs_pct_at_trigger":83,"vol_ratio_at_trigger":0.66,"market_regime_at_trigger":"bull","max_gain_pct":0.0,"max_loss_pct":0.0,"day_of_max_gain":0,"exit_reason":null},{"code":"4906","name":"正文","type":"retest","label":"縮量回測(主升型)","strength":"medium","trigger_date":"2026-04-15","trigger_price":39.95,"entry":39.55,"stop_loss":31.17,"atr_stop":31.17,"target":57.65,"rr":2.16,"confirmations":2,"confirmation_flags":["RS強勢","大盤多頭"],"exit_style":"fixed","status":"open","repeat":false,"is_pyramid":false,"sector_key":"通信網路","sector_phase":"主升回檔","current_price":39.55,"days_held":0,"gain_pct":0.0,"resolved_date":null,"rs_pct_at_trigger":74,"vol_ratio_at_trigger":0.71,"market_regime_at_trigger":"bull","max_gain_pct":0.0,"max_loss_pct":0.0,"day_of_max_gain":0,"exit_reason":null},{"code":"1305","name":"華夏","type":"retest","label":"縮量回測(主升型)","strength":"medium","trigger_date":"2026-04-15","trigger_price":17.79,"entry":17.0,"stop_loss":13.3,"atr_stop":13.3,"target":24.99,"rr":2.16,"confirmations":2,"confirmation_flags":["RS強勢","大盤多頭"],"exit_style":"fixed","status":"open","repeat":false,"is_pyramid":false,"sector_key":"化學","sector_phase":"主升回檔","current_price":17.0,"days_held":0,"gain_pct":0.0,"resolved_date":null,"rs_pct_at_trigger":74,"vol_ratio_at_trigger":0.41,"market_regime_at_trigger":"bull","max_gain_pct":0.0,"max_loss_pct":0.0,"day_of_max_gain":0,"exit_reason":null},{"code":"1723","name":"中碳","type":"retest","label":"縮量回測(起漲型)","strength":"weak","trigger_date":"2026-04-15","trigger_price":82.61,"entry":81.9,"stop_loss":75.02,"atr_stop":75.02,"target":96.76,"rr":2.16,"confirmations":1,"confirmation_flags":["大盤多頭"],"exit_style":"fixed","status":"open","repeat":false,"is_pyramid":false,"sector_key":"化學","sector_phase":"主升回檔","current_price":81.9,"days_held":0,"gain_pct":0.0,"resolved_date":null,"rs_pct_at_trigger":48,"vol_ratio_at_trigger":0.52,"market_regime_at_trigger":"bull","max_gain_pct":0.0,"max_loss_pct":0.0,"day_of_max_gain":0,"exit_reason":null}],"signal_archive":[],"stocks":[{"code":"1528","name":"恩德","price":30.35,"chg_pct":9.96,"vol_ratio":1.67,"ma5":27.91,"ma20":25.19,"ma60":25.09,"avwap_swing":26.28,"avwap_vol":27.34,"avwap_short":28.46,"industry":"電機機械","rs_pct":71,"stock_phase":"BULL","m_z":5.0,"rs_trend":1.8848,"signals":[{"type":"high_base","label":"強整再突","strength":"strong","strategy":"trend","entry":30.35,"trigger_price":30.44,"stop_loss":25.08,"atr_stop":25.08,"target":53.12,"risk":5.27,"rr":4.32,"risk_pct":17.36,"pos_factor":0.3,"reason":"緊貼20日高(30.35)整理，RS百分位71；主力未跑✓","timeframe":"medium","confirmations":5,"confirmation_flags":[{"lbl":"籌碼偏多","sub":"主力籌碼分>60","ok":false},{"lbl":"RS強勢","sub":"RS百分位≥70","ok":true},{"lbl":"量能擴張","sub":"日量比>1.3×","ok":true},{"lbl":"個股多頭","sub":"個股相位=BULL","ok":true},{"lbl":"大盤多頭","sub":"大盤相位=多頭","ok":true},{"lbl":"均量線對齊","sub":"三條AVWAP均低於現價","ok":true}],"exit_style":"trailing"}],"patterns":[]},{"code":"2399","name":"映泰","price":37.05,"chg_pct":9.94,"vol_ratio":1.62,"ma5":34.68,"ma20":32.95,"ma60":27.35,"avwap_swing":32.85,"avwap_vol":35.05,"avwap_short":34.74,"industry":"電腦週邊","rs_pct":74,"stock_phase":"BULL","m_z":5.0,"rs_trend":3.6162,"signals":[{"type":"high_base","label":"強整再突","strength":"strong","strategy":"trend","entry":37.05,"trigger_price":37.16,"stop_loss":30.9,"atr_stop":30.9,"target":63.62,"risk":6.15,"rr":4.32,"risk_pct":16.6,"pos_factor":0.3,"reason":"緊貼20日高(37.95)整理，RS百分位74；主力未跑✓","timeframe":"medium","confirmations":5,"confirmation_flags":[{"lbl":"籌碼偏多","sub":"主力籌碼分>60","ok":false},{"lbl":"RS強勢","sub":"RS百分位≥70","ok":true},{"lbl":"量能擴張","sub":"日量比>1.3×","ok":true},{"lbl":"個股多頭","sub":"個股相位=BULL","ok":true},{"lbl":"大盤多頭","sub":"大盤相位=多頭","ok":true},{"lbl":"均量線對齊","sub":"三條AVWAP均低於現價","ok":true}],"exit_style":"trailing"}],"patterns":[]},{"code":"2484","name":"希華","price":36.65,"chg_pct":6.39,"vol_ratio":3.32,"ma5":33.63,"ma20":30.1,"ma60":28.27,"avwap_swing":30.76,"avwap_vol":36.08,"avwap_short":34.71,"industry":"電子零組件","rs_pct":85,"stock_phase":"BULL","m_z":3.4149,"rs_trend":0.3175,"signals":[{"type":"high_base","label":"強整再突","strength":"strong","strategy":"trend","entry":36.65,"trigger_price":37.96,"stop_loss":30.35,"atr_stop":30.35,"target":63.87,"risk":6.3,"rr":4.32,"risk_pct":17.19,"pos_factor":0.3,"reason":"緊貼20日高(38.35)整理，RS百分位85；主力未跑✓","timeframe":"medium","confirmations":5,"confirmation_flags":[{"lbl":"籌碼偏多","sub":"主力籌碼分>60","ok":false},{"lbl":"RS強勢","sub":"RS百分位≥70","ok":true},{"lbl":"量能擴張","sub":"日量比>1.3×","ok":true},{"lbl":"個股多頭","sub":"個股相位=BULL","ok":true},{"lbl":"大盤多頭","sub":"大盤相位=多頭","ok":true},{"lbl":"均量線對齊","sub":"三條AVWAP均低於現價","ok":true}],"exit_style":"trailing"}],"patterns":[]},{"code":"6456","name":"GIS-KY","price":70.1,"chg_pct":9.87,"vol_ratio":4.0,"ma5":59.76,"ma20":58.93,"ma60":50.9,"avwap_swing":58.76,"avwap_vol":67.43,"avwap_short":65.02,"industry":"電子零組件","rs_pct":81,"stock_phase":"BULL","m_z":5.0,"rs_trend":3.5006,"signals":[{"type":"high_base","label":"強整再突","strength":"strong","strategy":"trend","entry":70.1,"trigger_price":70.31,"stop_loss":58.17,"atr_stop":60.3,"target":121.64,"risk":11.93,"rr":4.32,"risk_pct":17.02,"pos_factor":0.3,"reason":"緊貼20日高(70.1)整理，RS百分位81；主力未跑✓","timeframe":"medium","confirmations":5,"confirmation_flags":[{"lbl":"籌碼偏多","sub":"主力籌碼分>60","ok":false},{"lbl":"RS強勢","sub":"RS百分位≥70","ok":true},{"lbl":"量能擴張","sub":"日量比>1.3×","ok":true},{"lbl":"個股多頭","sub":"個股相位=BULL","ok":true},{"lbl":"大盤多頭","sub":"大盤相位=多頭","ok":true},{"lbl":"均量線對齊","sub":"三條AVWAP均低於現價","ok":true}],"exit_style":"trailing"}],"patterns":[]},{"code":"3645","name":"達邁","price":93.5,"chg_pct":5.17,"vol_ratio":2.3,"ma5":85.96,"ma20":78.86,"ma60":69.06,"avwap_swing":75.65,"avwap_vol":91.22,"avwap_short":86.26,"industry":"電子零組件","rs_pct":86,"stock_phase":"BULL","m_z":3.4897,"rs_trend":0.0443,"signals":[{"type":"high_base","label":"強整再突","strength":"strong","strategy":"trend","entry":93.5,"trigger_price":93.88,"stop_loss":74.89,"atr_stop":79.83,"target":173.9,"risk":18.61,"rr":4.32,"risk_pct":19.9,"pos_factor":0.3,"reason":"緊貼20日高(97.1)整理，RS百分位86；主力未跑✓","timeframe":"medium","confirmations":5,"confirmation_flags":[{"lbl":"籌碼偏多","sub":"主力籌碼分>60","ok":false},{"lbl":"RS強勢","sub":"RS百分位≥70","ok":true},{"lbl":"量能擴張","sub":"日量比>1.3×","ok":true},{"lbl":"個股多頭","sub":"個股相位=BULL","ok":true},{"lbl":"大盤多頭","sub":"大盤相位=多頭","ok":true},{"lbl":"均量線對齊","sub":"三條AVWAP均低於現價","ok":true}],"exit_style":"trailing"}],"patterns":[]},{"code":"3711","name":"日月光投控","price":446.5,"chg_pct":5.31,"vol_ratio":1.59,"ma5":414.6,"ma20":366.45,"ma60":336.0,"avwap_swing":338.79,"avwap_vol":445.83,"avwap_short":405.4,"industry":"半導體","rs_pct":80,"stock_phase":"BULL","m_z":3.3437,"rs_trend":0.4673,"signals":[{"type":"high_base","label":"強整再突","strength":"strong","strategy":"trend","entry":446.5,"trigger_price":461.38,"stop_loss":335.4,"atr_stop":390.7,"target":926.45,"risk":111.1,"rr":4.32,"risk_pct":24.88,"pos_factor":0.3,"reason":"緊貼20日高(460.0)整理，RS百分位80；主力未跑✓","timeframe":"medium","confirmations":5,"confirmation_flags":[{"lbl":"籌碼偏多","sub":"主力籌碼分>60","ok":false},{"lbl":"RS強勢","sub":"RS百分位≥70","ok":true},{"lbl":"量能擴張","sub":"日量比>1.3×","ok":true},{"lbl":"個股多頭","sub":"個股相位=BULL","ok":true},{"lbl":"大盤多頭","sub":"大盤相位=多頭","ok":true},{"lbl":"均量線對齊","sub":"三條AVWAP均低於現價","ok":true}],"exit_style":"trailing"}],"patterns":[]},{"code":"2049","name":"上銀","price":282.0,"chg_pct":2.55,"vol_ratio":4.59,"ma5":258.8,"ma20":239.0,"ma60":234.05,"avwap_swing":242.64,"avwap_vol":281.0,"avwap_short":270.93,"industry":"其他","rs_pct":72,"stock_phase":"BULL","m_z":5.0,"rs_trend":1.0875,"signals":[{"type":"high_base","label":"強整再突","strength":"strong","strategy":"trend","entry":282.0,"trigger_price":294.88,"stop_loss":240.21,"atr_stop":244.6,"target":462.53,"risk":41.79,"rr":4.32,"risk_pct":14.82,"pos_factor":0.3,"reason":"緊貼20日高(294.0)整理，RS百分位72；主力未跑✓","timeframe":"medium","confirmations":5,"confirmation_flags":[{"lbl":"籌碼偏多","sub":"主力籌碼分>60","ok":false},{"lbl":"RS強勢","sub":"RS百分位≥70","ok":true},{"lbl":"量能擴張","sub":"日量比>1.3×","ok":true},{"lbl":"個股多頭","sub":"個股相位=BULL","ok":true},{"lbl":"大盤多頭","sub":"大盤相位=多頭","ok":true},{"lbl":"均量線對齊","sub":"三條AVWAP均低於現價","ok":true}],"exit_style":"trailing"}],"patterns":[]},{"code":"6271","name":"同欣電","price":183.0,"chg_pct":3.98,"vol_ratio":3.95,"ma5":175.1,"ma20":157.97,"ma60":151.38,"avwap_swing":158.7,"avwap_vol":180.5,"avwap_short":170.16,"industry":"半導體","rs_pct":73,"stock_phase":"BULL","m_z":2.8125,"rs_trend":0.3264,"signals":[{"type":"high_base","label":"強整再突","strength":"strong","strategy":"trend","entry":183.0,"trigger_price":188.56,"stop_loss":157.11,"atr_stop":159.78,"target":294.84,"risk":25.89,"rr":4.32,"risk_pct":14.15,"pos_factor":0.3,"reason":"緊貼20日高(188.0)整理，RS百分位73；主力未跑✓","timeframe":"medium","confirmations":5,"confirmation_flags":[{"lbl":"籌碼偏多","sub":"主力籌碼分>60","ok":false},{"lbl":"RS強勢","sub":"RS百分位≥70","ok":true},{"lbl":"量能擴張","sub":"日量比>1.3×","ok":true},{"lbl":"個股多頭","sub":"個股相位=BULL","ok":true},{"lbl":"大盤多頭","sub":"大盤相位=多頭","ok":true},{"lbl":"均量線對齊","sub":"三條AVWAP均低於現價","ok":true}],"exit_style":"trailing"}],"patterns":[]},{"code":"6438","name":"迅得","price":176.0,"chg_pct":-2.22,"vol_ratio":0.43,"ma5":179.2,"ma20":172.0,"ma60":156.45,"avwap_swing":165.19,"avwap_vol":176.33,"avwap_short":179.89,"industry":"電機機械","rs_pct":65,"stock_phase":"RANGE","m_z":3.5133,"rs_trend":-1.0364,"signals":[{"type":"ma_pullback","label":"均線回測(主升型)","strength":"medium","strategy":"trend","entry":176.0,"trigger_price":182.41,"stop_loss":151.9,"atr_stop":151.9,"target":228.06,"risk":24.1,"rr":2.16,"risk_pct":13.69,"pos_factor":0.3,"reason":"均線多頭，RS百分位65(≥60)","timeframe":"medium","confirmations":1,"confirmation_flags":[{"lbl":"籌碼偏多","sub":"主力籌碼分>60","ok":false},{"lbl":"RS強勢","sub":"RS百分位≥70","ok":false},{"lbl":"量能擴張","sub":"日量比>1.3×","ok":false},{"lbl":"個股多頭","sub":"個股相位=BULL","ok":false},{"lbl":"大盤多頭","sub":"大盤相位=多頭","ok":true},{"lbl":"均量線對齊","sub":"三條AVWAP均低於現價","ok":false}],"exit_style":"fixed"},{"type":"retest","label":"縮量回測(主升型)","strength":"medium","strategy":"trend","entry":176.0,"trigger_price":182.41,"stop_loss":151.9,"atr_stop":151.9,"target":228.06,"risk":24.1,"rr":2.16,"risk_pct":13.69,"pos_factor":0.3,"reason":"縮量(0.4x)回測MA10(175.25)，RS百分位65(≥60)","timeframe":"short","confirmations":1,"confirmation_flags":[{"lbl":"籌碼偏多","sub":"主力籌碼分>60","ok":false},{"lbl":"RS強勢","sub":"RS百分位≥70","ok":false},{"lbl":"量能擴張","sub":"日量比>1.3×","ok":false},{"lbl":"個股多頭","sub":"個股相位=BULL","ok":false},{"lbl":"大盤多頭","sub":"大盤相位=多頭","ok":true},{"lbl":"均量線對齊","sub":"三條AVWAP均低於現價","ok":false}],"exit_style":"fixed"}],"patterns":[]},{"code":"3715","name":"定穎投控","price":185.5,"chg_pct":-0.54,"vol_ratio":0.64,"ma5":186.4,"ma20":181.45,"ma60":156.97,"avwap_swing":158.03,"avwap_vol":187.28,"avwap_short":186.15,"industry":"電子零組件","rs_pct":72,"stock_phase":"BULL","m_z":1.4941,"rs_trend":0.4365,"signals":[{"type":"ma_pullback","label":"均線回測(主升型)","strength":"medium","strategy":"trend","entry":185.5,"trigger_price":192.96,"stop_loss":153.62,"atr_stop":153.62,"target":323.22,"risk":31.88,"rr":4.32,"risk_pct":17.19,"pos_factor":0.3,"reason":"均線多頭，RS百分位72(≥60)","timeframe":"medium","confirmations":3,"confirmation_flags":[{"lbl":"籌碼偏多","sub":"主力籌碼分>60","ok":false},{"lbl":"RS強勢","sub":"RS百分位≥70","ok":true},{"lbl":"量能擴張","sub":"日量比>1.3×","ok":false},{"lbl":"個股多頭","sub":"個股相位=BULL","ok":true},{"lbl":"大盤多頭","sub":"大盤相位=多頭","ok":true},{"lbl":"均量線對齊","sub":"三條AVWAP均低於現價","ok":false}],"exit_style":"fixed"},{"type":"retest","label":"縮量回測(主升型)","strength":"medium","strategy":"trend","entry":185.5,"trigger_price":192.96,"stop_loss":153.62,"atr_stop":153.62,"target":323.22,"risk":31.88,"rr":4.32,"risk_pct":17.19,"pos_factor":0.3,"reason":"縮量(0.6x)回測MA10(183.5)，RS百分位72(≥60)","timeframe":"short","confirmations":3,"confirmation_flags":[{"lbl":"籌碼偏多","sub":"主力籌碼分>60","ok":false},{"lbl":"RS強勢","sub":"RS百分位≥70","ok":true},{"lbl":"量能擴張","sub":"日量比>1.3×","ok":false},{"lbl":"個股多頭","sub":"個股相位=BULL","ok":true},{"lbl":"大盤多頭","sub":"大盤相位=多頭","ok":true},{"lbl":"均量線對齊","sub":"三條AVWAP均低於現價","ok":false}],"exit_style":"fixed"}],"patterns":[]},{"code":"2455","name":"全新","price":275.0,"chg_pct":-1.96,"vol_ratio":0.15,"ma5":287.1,"ma20":261.32,"ma60":212.0,"avwap_swing":217.65,"avwap_vol":277.24,"avwap_short":286.15,"industry":"半導體","rs_pct":86,"stock_phase":"RANGE","m_z":2.9906,"rs_trend":-1.2828,"signals":[{"type":"retest","label":"縮量回測(主升型)","strength":"medium","strategy":"trend","entry":275.0,"trigger_price":283.41,"stop_loss":223.65,"atr_stop":223.65,"target":385.92,"risk":51.35,"rr":2.16,"risk_pct":18.67,"pos_factor":0.3,"reason":"縮量(0.1x)回測MA10(277.95)，RS百分位86(≥60)","timeframe":"short","confirmations":2,"confirmation_flags":[{"lbl":"籌碼偏多","sub":"主力籌碼分>60","ok":false},{"lbl":"RS強勢","sub":"RS百分位≥70","ok":true},{"lbl":"量能擴張","sub":"日量比>1.3×","ok":false},{"lbl":"個股多頭","sub":"個股相位=BULL","ok":false},{"lbl":"大盤多頭","sub":"大盤相位=多頭","ok":true},{"lbl":"均量線對齊","sub":"三條AVWAP均低於現價","ok":false}],"exit_style":"fixed"}],"patterns":[]},{"code":"2360","name":"致茂","price":2020.0,"chg_pct":9.78,"vol_ratio":0.69,"ma5":1873.0,"ma20":1649.5,"ma60":1308.78,"avwap_swing":1363.81,"avwap_vol":1856.09,"avwap_short":1718.69,"industry":"電子工業","rs_pct":93,"stock_phase":"BULL","m_z":5.0,"rs_trend":0.4551,"signals":[{"type":"high_base","label":"強整再突","strength":"medium","strategy":"trend","entry":2020.0,"trigger_price":2026.06,"stop_loss":1350.17,"atr_stop":1680.72,"target":4913.67,"risk":669.83,"rr":4.32,"risk_pct":33.16,"pos_factor":0.3,"reason":"緊貼20日高(2020.0)整理，RS百分位93；主力未跑✓","timeframe":"medium","confirmations":4,"confirmation_flags":[{"lbl":"籌碼偏多","sub":"主力籌碼分>60","ok":false},{"lbl":"RS強勢","sub":"RS百分位≥70","ok":true},{"lbl":"量能擴張","sub":"日量比>1.3×","ok":false},{"lbl":"個股多頭","sub":"個股相位=BULL","ok":true},{"lbl":"大盤多頭","sub":"大盤相位=多頭","ok":true},{"lbl":"均量線對齊","sub":"三條AVWAP均低於現價","ok":true}],"exit_style":"trailing"}],"patterns":[]},{"code":"4989","name":"榮科","price":98.3,"chg_pct":9.96,"vol_ratio":0.64,"ma5":84.62,"ma20":71.98,"ma60":63.7,"avwap_swing":70.62,"avwap_vol":74.4,"avwap_short":78.14,"industry":"鋼鐵","rs_pct":90,"stock_phase":"BULL","m_z":2.8011,"rs_trend":0.5553,"signals":[{"type":"high_base","label":"強整再突","strength":"medium","strategy":"trend","entry":98.3,"trigger_price":98.59,"stop_loss":69.91,"atr_stop":84.9,"target":220.94,"risk":28.39,"rr":4.32,"risk_pct":28.88,"pos_factor":0.3,"reason":"緊貼20日高(98.3)整理，RS百分位90；主力未跑✓","timeframe":"medium","confirmations":4,"confirmation_flags":[{"lbl":"籌碼偏多","sub":"主力籌碼分>60","ok":false},{"lbl":"RS強勢","sub":"RS百分位≥70","ok":true},{"lbl":"量能擴張","sub":"日量比>1.3×","ok":false},{"lbl":"個股多頭","sub":"個股相位=BULL","ok":true},{"lbl":"大盤多頭","sub":"大盤相位=多頭","ok":true},{"lbl":"均量線對齊","sub":"三條AVWAP均低於現價","ok":true}],"exit_style":"trailing"}],"patterns":[]},{"code":"2383","name":"台光電","price":3810.0,"chg_pct":5.69,"vol_ratio":1.17,"ma5":3476.0,"ma20":2987.25,"ma60":2332.67,"avwap_swing":2304.47,"avwap_vol":3002.88,"avwap_short":3162.31,"industry":"電子零組件","rs_pct":96,"stock_phase":"BULL","m_z":2.1649,"rs_trend":0.7886,"signals":[{"type":"high_base","label":"強整再突","strength":"medium","strategy":"trend","entry":3810.0,"trigger_price":3886.62,"stop_loss":2281.43,"atr_stop":3274.28,"target":10413.42,"risk":1528.57,"rr":4.32,"risk_pct":40.12,"pos_factor":0.3,"reason":"緊貼20日高(3875.0)整理，RS百分位96；主力未跑✓","timeframe":"medium","confirmations":4,"confirmation_flags":[{"lbl":"籌碼偏多","sub":"主力籌碼分>60","ok":false},{"lbl":"RS強勢","sub":"RS百分位≥70","ok":true},{"lbl":"量能擴張","sub":"日量比>1.3×","ok":false},{"lbl":"個股多頭","sub":"個股相位=BULL","ok":true},{"lbl":"大盤多頭","sub":"大盤相位=多頭","ok":true},{"lbl":"均量線對齊","sub":"三條AVWAP均低於現價","ok":true}],"exit_style":"trailing"}],"patterns":[]},{"code":"3017","name":"奇鋐","price":2325.0,"chg_pct":0.65,"vol_ratio":0.66,"ma5":2267.0,"ma20":2111.5,"ma60":1745.67,"avwap_swing":1777.66,"avwap_vol":2113.33,"avwap_short":2290.54,"industry":"電子零組件","rs_pct":83,"stock_phase":"BULL","m_z":1.828,"rs_trend":0.1965,"signals":[{"type":"high_base","label":"強整再突","strength":"medium","strategy":"trend","entry":2325.0,"trigger_price":2382.12,"stop_loss":1759.88,"atr_stop":1984.83,"target":4766.32,"risk":565.12,"rr":4.32,"risk_pct":24.31,"pos_factor":0.3,"reason":"緊貼20日高(2375.0)整理，RS百分位83；主力未跑✓","timeframe":"medium","confirmations":4,"confirmation_flags":[{"lbl":"籌碼偏多","sub":"主力籌碼分>60","ok":false},{"lbl":"RS強勢","sub":"RS百分位≥70","ok":true},{"lbl":"量能擴張","sub":"日量比>1.3×","ok":false},{"lbl":"個股多頭","sub":"個股相位=BULL","ok":true},{"lbl":"大盤多頭","sub":"大盤相位=多頭","ok":true},{"lbl":"均量線對齊","sub":"三條AVWAP均低於現價","ok":true}],"exit_style":"trailing"}],"patterns":[]},{"code":"4906","name":"正文","price":39.55,"chg_pct":0.64,"vol_ratio":0.71,"ma5":39.97,"ma20":36.38,"ma60":30.34,"avwap_swing":37.53,"avwap_vol":39.71,"avwap_short":40.17,"industry":"通信網路","rs_pct":74,"stock_phase":"RANGE","m_z":-5.0,"rs_trend":-0.9313,"signals":[{"type":"retest","label":"縮量回測(主升型)","strength":"medium","strategy":"trend","entry":39.55,"trigger_price":39.95,"stop_loss":31.17,"atr_stop":31.17,"target":57.65,"risk":8.38,"rr":2.16,"risk_pct":21.19,"pos_factor":0.3,"reason":"縮量(0.7x)回測MA10(39.05)，RS百分位74(≥60)","timeframe":"short","confirmations":2,"confirmation_flags":[{"lbl":"籌碼偏多","sub":"主力籌碼分>60","ok":false},{"lbl":"RS強勢","sub":"RS百分位≥70","ok":true},{"lbl":"量能擴張","sub":"日量比>1.3×","ok":false},{"lbl":"個股多頭","sub":"個股相位=BULL","ok":false},{"lbl":"大盤多頭","sub":"大盤相位=多頭","ok":true},{"lbl":"均量線對齊","sub":"三條AVWAP均低於現價","ok":false}],"exit_style":"fixed"}],"patterns":[]},{"code":"1305","name":"華夏","price":17.0,"chg_pct":-3.68,"vol_ratio":0.41,"ma5":17.07,"ma20":16.8,"ma60":13.78,"avwap_swing":15.78,"avwap_vol":17.38,"avwap_short":16.8,"industry":"化學","rs_pct":74,"stock_phase":"RANGE","m_z":2.5282,"rs_trend":-1.7742,"signals":[{"type":"retest","label":"縮量回測(主升型)","strength":"medium","strategy":"trend","entry":17.0,"trigger_price":17.79,"stop_loss":13.3,"atr_stop":13.3,"target":24.99,"risk":3.7,"rr":2.16,"risk_pct":21.76,"pos_factor":0.3,"reason":"縮量(0.4x)回測MA10(17.11)，RS百分位74(≥60)","timeframe":"short","confirmations":2,"confirmation_flags":[{"lbl":"籌碼偏多","sub":"主力籌碼分>60","ok":false},{"lbl":"RS強勢","sub":"RS百分位≥70","ok":true},{"lbl":"量能擴張","sub":"日量比>1.3×","ok":false},{"lbl":"個股多頭","sub":"個股相位=BULL","ok":false},{"lbl":"大盤多頭","sub":"大盤相位=多頭","ok":true},{"lbl":"均量線對齊","sub":"三條AVWAP均低於現價","ok":false}],"exit_style":"fixed"}],"patterns":[]},{"code":"1723","name":"中碳","price":81.9,"chg_pct":0.61,"vol_ratio":0.52,"ma5":79.96,"ma20":79.32,"ma60":74.26,"avwap_swing":81.18,"avwap_vol":83.62,"avwap_short":79.81,"industry":"化學","rs_pct":48,"stock_phase":"RANGE","m_z":0.2797,"rs_trend":0.0071,"signals":[{"type":"retest","label":"縮量回測(起漲型)","strength":"weak","strategy":"swing","entry":81.9,"trigger_price":82.61,"stop_loss":75.02,"atr_stop":75.02,"target":96.76,"risk":6.88,"rr":2.16,"risk_pct":8.4,"pos_factor":0.3,"reason":"縮量(0.5x)回測MA10(82.26)，RS百分位48(40~60)，RS斜率剛翻正","timeframe":"short","confirmations":1,"confirmation_flags":[{"lbl":"籌碼偏多","sub":"主力籌碼分>60","ok":false},{"lbl":"RS強勢","sub":"RS百分位≥70","ok":false},{"lbl":"量能擴張","sub":"日量比>1.3×","ok":false},{"lbl":"個股多頭","sub":"個股相位=BULL","ok":false},{"lbl":"大盤多頭","sub":"大盤相位=多頭","ok":true},{"lbl":"均量線對齊","sub":"三條AVWAP均低於現價","ok":false}],"exit_style":"fixed"}],"patterns":[]},{"code":"2887","name":"台新新光金","price":24.6,"chg_pct":0.61,"vol_ratio":0.77,"ma5":24.48,"ma20":24.31,"ma60":23.64,"avwap_swing":23.75,"avwap_vol":24.11,"avwap_short":24.39,"industry":"金融保險","rs_pct":49,"stock_phase":"RANGE","m_z":0.6357,"rs_trend":0.0738,"signals":[{"type":"retest","label":"縮量回測(起漲型)","strength":"weak","strategy":"swing","entry":24.6,"trigger_price":24.92,"stop_loss":23.71,"atr_stop":23.71,"target":26.52,"risk":0.89,"rr":2.16,"risk_pct":3.62,"pos_factor":0.41,"reason":"縮量(0.8x)回測MA10(24.3)，RS百分位49(40~60)，RS斜率剛翻正；主力未跑✓","timeframe":"short","confirmations":2,"confirmation_flags":[{"lbl":"籌碼偏多","sub":"主力籌碼分>60","ok":false},{"lbl":"RS強勢","sub":"RS百分位≥70","ok":false},{"lbl":"量能擴張","sub":"日量比>1.3×","ok":false},{"lbl":"個股多頭","sub":"個股相位=BULL","ok":false},{"lbl":"大盤多頭","sub":"大盤相位=多頭","ok":true},{"lbl":"均量線對齊","sub":"三條AVWAP均低於現價","ok":true}],"exit_style":"fixed"}],"patterns":[]}]}